logfury/__init__.py
logfury/_logfury/__init__.py
logfury/_logfury/meta.py
logfury/_logfury/trace_call.py
logfury/_logfury/tuning.py
logfury/v0_1/__init__.py
logfury/v1/__init__.py
logfury-1.0.0.dist-info/LICENSE
logfury-1.0.0.dist-info/METADATA
logfury-1.0.0.dist-info/WHEEL
logfury-1.0.0.dist-info/top_level.txt
logfury-1.0.0.dist-info/RECORD
