Metadata-Version: 2.1
Name: logfury
Version: 1.0.0
Summary: ('Toolkit for responsible, low-boilerplate logging of library method calls',)
Home-page: https://github.com/reef-technologies/logfury
Author: Pawel Polewicz
Author-email: p.polewicz@gmail.com
Maintainer: Pawel Polewicz
Maintainer-email: p.polewicz@gmail.com
License: BSD
Download-URL: https://github.com/reef-technologies/logfury/releases
Keywords: logging,tracing
Platform: UNKNOWN
Classifier: Development Status :: 6 - Mature
Classifier: Intended Audience :: Developers
Classifier: Topic :: Software Development :: Libraries :: Python Modules
Classifier: Topic :: System :: Logging
Classifier: Natural Language :: English
Classifier: License :: OSI Approved :: BSD License
Classifier: Operating System :: OS Independent
Classifier: Programming Language :: Python
Classifier: Programming Language :: Python :: 3
Classifier: Programming Language :: Python :: 3.5
Classifier: Programming Language :: Python :: 3.6
Classifier: Programming Language :: Python :: 3.7
Classifier: Programming Language :: Python :: 3.8
Classifier: Programming Language :: Python :: 3.9
Classifier: Programming Language :: Python :: 3.10
Classifier: Programming Language :: Python :: Implementation :: CPython
Classifier: Programming Language :: Python :: Implementation :: PyPy
License-File: LICENSE
